[null,{"name":"Weather","permissions":"NONE","restriction":"4","_id":"nTwii","actions":[{"info":"1","infoIndex":"1","storage":"1","varName":"prm","name":"Store Command Params"},{"city":"${tempVars(\"prm\")}","degreeType":"C","info":"15","storage":"1","varName":"snd","name":"Weather"},{"city":"${tempVars(\"prm\")}","degreeType":"C","info":"0","storage":"1","varName":"temp","name":"Weather"},{"city":"${tempVars(\"prm\")}","degreeType":"C","info":"14","storage":"1","varName":"ftemp","name":"Weather"},{"city":"${tempVars(\"prm\")}","degreeType":"C","info":"2","storage":"1","varName":"date","name":"Weather"},{"city":"${tempVars(\"prm\")}","degreeType":"C","info":"16","storage":"1","varName":"day","name":"Weather"},{"city":"${tempVars(\"prm\")}","degreeType":"C","info":"9","storage":"1","varName":"humidity","name":"Weather"},{"city":"${tempVars(\"prm\")}","degreeType":"C","info":"4","storage":"1","varName":"country","name":"Weather"},{"city":"${tempVars(\"prm\")}","degreeType":"C","info":"6","storage":"1","varName":"WSPEED","name":"Weather"},{"city":"${tempVars(\"prm\")}","degreeType":"C","info":"8","storage":"1","varName":"Wdirect","name":"Weather"},{"title":"TuxBot","author":"","color":"#FF8C00","timestamp":"true","url":"","authorIcon":"","imageUrl":"","thumbUrl":"${tempVars(\"snd\")}","storage":"1","varName":"embd","name":"Create Embed Message"},{"storage":"1","varName":"embd","message":"**Information on ${tempVars(\"prm\")}, in ${tempVars(\"country\")}.**\n\n**DATE:**           ${tempVars(\"date\")}\n**DAY:**            ${tempVars(\"day\")}   \n\n**WEATHER:**        ${tempVars(\"temp\")}°C\n**FEELS LIKE:**     ${tempVars(\"ftemp\")}°C\n**HUMIDITY:**       ${tempVars(\"humidity\")}%\n\n**WIND SPEED:**     ${tempVars(\"WSPEED\")}\n**WIND DIRECTION:** ${tempVars(\"Wdirect\")}","name":"Set Embed Description"},{"storage":"1","varName":"embd","message":"TuxBot 🐧","footerIcon":"","name":"Set Embed Footer"},{"storage":"1","varName":"embd","channel":"0","varName2":"","storage3":"0","varName3":"","name":"Send Embed Message"}],"comType":"0"},{"name":"Kick","permissions":"KICK_MEMBERS","restriction":"1","_id":"KQtyV","actions":[{"title":"TuxBot","author":"Requested by: ${serverVars(\"usern\")}${serverVars(\"discrm\")}${serverVars(\"discrm\")}${serverVars(\"discrm\")}      ","color":"ORANGE","timestamp":"true","url":"","authorIcon":"${serverVars(\"url\")}","imageUrl":"","thumbUrl":"","storage":"1","varName":"embd","name":"Create Embed Message"},{"storage":"1","varName":"embd","message":"Kicked ${mentionedUser}","name":"Set Embed Description"},{"storage":"1","varName":"embd","message":"TuxBot 🐧","footerIcon":"","name":"Set Embed Footer"},{"storage":"1","varName":"embd","channel":"0","varName2":"","storage3":"0","varName3":"","name":"Send Embed Message"},{"member":"0","varName":"","reason":"$ kicked $","name":"Kick Member"}]},{"name":"Nuke","permissions":"ADMINISTRATOR","restriction":"1","_id":"Kpxoa","actions":[{"channel":"0","varName":"","message":"Nuking ${msg.channel} :red_circle: :red_circle: :red_circle:","storage":"1","varName2":"nukemsg","name":"Send Message"},{"channel":"0","varName":"","message":"https://giphy.com/gifs/movie-vintage-1960s-3og0IFEYjQPvj8C5UI","storage":"1","varName2":"nukegif","name":"Send Message"},{"time":"1","measurement":"1","name":"Wait"},{"storage":"1","varName":"nukemsg","message":"Nuking ${msg.channel} :green_circle: :red_circle: :red_circle:","name":"Edit Message"},{"channel":"0","count":"300","condition":"0","custom":"","varName":"","name":"Delete Bulk Messages"},{"time":"1","measurement":"1","name":"Wait"},{"storage":"1","varName":"nukemsg","message":"Nuking ${msg.channel} :green_circle: :green_circle: :red_circle:","name":"Edit Message"},{"channel":"0","count":"3000","condition":"0","custom":"","varName":"","name":"Delete Bulk Messages"},{"time":"1","measurement":"1","name":"Wait"},{"storage":"1","varName":"nukemsg","message":"Nuking ${msg.channel} :green_circle: :green_circle: :green_circle:","name":"Edit Message"},{"time":"5","measurement":"1","name":"Wait"},{"storage":"0","varName":"","reason":"","name":"Delete Message"},{"storage":"1","varName":"nukemsg","reason":"","name":"Delete Message"},{"storage":"1","varName":"nukegif","reason":"","name":"Delete Message"}]},{"name":"Ban","permissions":"BAN_MEMBERS","restriction":"1","_id":"CyHCl","actions":[{"title":"TuxBot","author":"Requested by: ${serverVars(\"usern\")}${serverVars(\"discrm\")}${serverVars(\"discrm\")}${serverVars(\"discrm\")}      ","color":"RED","timestamp":"true","url":"","authorIcon":"${serverVars(\"url\")}","imageUrl":"","thumbUrl":"","storage":"1","varName":"embd","name":"Create Embed Message"},{"storage":"1","varName":"embd","message":"Kicked ${mentionedUser}","name":"Set Embed Description"},{"storage":"1","varName":"embd","message":"TuxBot 🐧","footerIcon":"","name":"Set Embed Footer"},{"storage":"1","varName":"embd","channel":"0","varName2":"","storage3":"0","varName3":"","name":"Send Embed Message"},{"member":"0","varName":"","reason":"$ Banned $","days":"","name":"Ban Member"}]},{"name":"Help","permissions":"NONE","restriction":"1","_id":"AVRtF","actions":[{"user":"1","varName":"","info":"4","storage":"2","varName2":"url","name":"Store User Info"},{"user":"1","varName":"","info":"2","storage":"2","varName2":"usern","name":"Store User Info"},{"user":"1","varName":"","info":"9","storage":"2","varName2":"discrm","name":"Store User Info"},{"title":"TuxBot","author":"Requested by: ${serverVars(\"usern\")}${serverVars(\"discrm\")}${serverVars(\"discrm\")}${serverVars(\"discrm\")}      ","color":"RANDOM","timestamp":"true","url":"","authorIcon":"${serverVars(\"url\")}","imageUrl":"","thumbUrl":"","storage":"1","varName":"embd","name":"Create Embed Message"},{"storage":"1","varName":"embd","message":"_**General**_\n**-Help**                    Shows this message\n\n_**Moderation**_             \n\n**-Kick [@user]**            Kicks pinged user.\n**-Ban [@user]**             Bans pinged user.\n**-Nuke**                    Deletes bulk messages in command channel\n\n\n\n\n","name":"Set Embed Description"},{"storage":"1","varName":"embd","message":"TuxBot 🐧","footerIcon":"","name":"Set Embed Footer"},{"storage":"1","varName":"embd","channel":"0","varName2":"","storage3":"0","varName3":"","name":"Send Embed Message"}],"customData":{"Command Info":{"category":"None","description":"No Description","include":"No"}}}]